{
"type": "FeatureCollection",
"name": "us_med_pnmgl_eoliennes_ancres_pt_4326",
"crs": { "type": "name", "properties": { "name": "urn:ogc:def:crs:OGC:1.3:CRS84" } },
"features": [
{ "type": "Feature", "properties": { "ID Ancre": "A01", "Latitude": 42.84242, "Longitude": 3.236376, "Y (Lambert": "6 193 689,78", "X (Lambert": "719 343,95" }, "geometry": { "type": "Point", "coordinates": [ 3.236376, 42.84242 ] } },
{ "type": "Feature", "properties": { "ID Ancre": "A02", "Latitude": 42.839777, "Longitude": 3.248723, "Y (Lambert": "6 193 399,03", "X (Lambert": "720 355,32" }, "geometry": { "type": "Point", "coordinates": [ 3.248723, 42.839777 ] } },
{ "type": "Feature", "properties": { "ID Ancre": "A03", "Latitude": 42.848444, "Longitude": 3.245044, "Y (Lambert": "6 194 361,92", "X (Lambert": "720 051,23" }, "geometry": { "type": "Point", "coordinates": [ 3.245044, 42.848444 ] } },
{ "type": "Feature", "properties": { "ID Ancre": "A04", "Latitude": 42.848007, "Longitude": 3.241538, "Y (Lambert": "6 194 312,40", "X (Lambert": "719 764,50" }, "geometry": { "type": "Point", "coordinates": [ 3.241538, 42.848007 ] } },
{ "type": "Feature", "properties": { "ID Ancre": "A05", "Latitude": 42.845364, "Longitude": 3.253886, "Y (Lambert": "6 194 021,65", "X (Lambert": "720 775,87" }, "geometry": { "type": "Point", "coordinates": [ 3.253886, 42.845364 ] } },
{ "type": "Feature", "properties": { "ID Ancre": "A06", "Latitude": 42.854031, "Longitude": 3.250207, "Y (Lambert": "6 194 984,54", "X (Lambert": "720 471,78" }, "geometry": { "type": "Point", "coordinates": [ 3.250207, 42.854031 ] } },
{ "type": "Feature", "properties": { "ID Ancre": "A07", "Latitude": 42.853592, "Longitude": 3.246689, "Y (Lambert": "6 194 934,82", "X (Lambert": "720 184,06" }, "geometry": { "type": "Point", "coordinates": [ 3.246689, 42.853592 ] } },
{ "type": "Feature", "properties": { "ID Ancre": "A08", "Latitude": 42.850949, "Longitude": 3.259038, "Y (Lambert": "6 194 644,08", "X (Lambert": "721 195,43" }, "geometry": { "type": "Point", "coordinates": [ 3.259038, 42.850949 ] } },
{ "type": "Feature", "properties": { "ID Ancre": "A09", "Latitude": 42.859616, "Longitude": 3.25536, "Y (Lambert": "6 195 606,97", "X (Lambert": "720 891,34" }, "geometry": { "type": "Point", "coordinates": [ 3.25536, 42.859616 ] } },
{ "type": "Feature", "properties": { "ID Ancre": "A10", "Latitude": 42.859181, "Longitude": 3.251844, "Y (Lambert": "6 195 557,64", "X (Lambert": "720 603,87" }, "geometry": { "type": "Point", "coordinates": [ 3.251844, 42.859181 ] } },
{ "type": "Feature", "properties": { "ID Ancre": "A11", "Latitude": 42.856537, "Longitude": 3.264194, "Y (Lambert": "6 195 266,89", "X (Lambert": "721 615,25" }, "geometry": { "type": "Point", "coordinates": [ 3.264194, 42.856537 ] } },
{ "type": "Feature", "properties": { "ID Ancre": "A12", "Latitude": 42.865204, "Longitude": 3.260517, "Y (Lambert": "6 196 229,78", "X (Lambert": "721 311,16" }, "geometry": { "type": "Point", "coordinates": [ 3.260517, 42.865204 ] } }
]
}
